straceprof/__init__.py
straceprof/__main__.py
straceprof/cli.py
straceprof-0.0.8.dist-info/METADATA
straceprof-0.0.8.dist-info/WHEEL
straceprof-0.0.8.dist-info/entry_points.txt
straceprof-0.0.8.dist-info/licenses/LICENSE
straceprof-0.0.8.dist-info/RECORD
