Metadata-Version: 2.4
Name: straceprof
Version: 0.0.8
Summary: Generate a profile graph from strace log
Project-URL: Repository, https://github.com/akawashiro/straceprof
Project-URL: Issues, https://github.com/akawashiro/straceprof/issues
Author: Akira Kawata
Maintainer: Akira Kawata
License: MIT License
License-File: LICENSE
Keywords: profiling,strace
Requires-Python: >=3.10
Requires-Dist: matplotlib
